whsk/__init__.py
whsk/user_agents.py
whsk-0.3.1.dist-info/METADATA
whsk-0.3.1.dist-info/WHEEL
whsk-0.3.1.dist-info/entry_points.txt
whsk-0.3.1.dist-info/RECORD
